smart_pathlib/__init__.py
smart_pathlib/gcs.py
smart_pathlib/library.py
smart_pathlib/local_file.py
smart_pathlib/transport.py
smart_pathlib/util.py
smart_pathlib/version.py
smart_pathlib-0.0.1.dist-info/LICENSE
smart_pathlib-0.0.1.dist-info/METADATA
smart_pathlib-0.0.1.dist-info/WHEEL
smart_pathlib-0.0.1.dist-info/top_level.txt
smart_pathlib-0.0.1.dist-info/RECORD
