Metadata-Version: 2.1
Name: smart-pathlib
Version: 0.0.1
Summary: Utils for making os standard path operationsinteroperable with Cloud blob storages
Home-page: https://github.com/gfournier/smart_pathlib
Author: Guillaume Fournier
Author-email: fournierg@gmail.com
Maintainer: Guillaume Fournier
Maintainer-email: fournierg@gmail.com
License: MIT
Download-URL: http://pypi.python.org/pypi/smart_pathlib
Keywords: s3,hdfs,gcs,azure blob storage
Platform: any
Classifier: Development Status :: 4 - Beta
Classifier: Environment :: Console
Classifier: Intended Audience :: Developers
Classifier: License :: OSI Approved :: MIT License
Classifier: Operating System :: OS Independent
Classifier: Programming Language :: Python :: 3.6
Classifier: Programming Language :: Python :: 3.7
Classifier: Programming Language :: Python :: 3.8
Classifier: Topic :: System :: Distributed Computing
Classifier: Topic :: Database :: Front-Ends
Requires-Python: >=3.6.*
Provides-Extra: all
Requires-Dist: google-cloud-storage ; extra == 'all'
Provides-Extra: gcp
Requires-Dist: google-cloud-storage ; extra == 'gcp'
Provides-Extra: test
Requires-Dist: google-cloud-storage ; extra == 'test'
Requires-Dist: pytest ; extra == 'test'
